google/__init__.py
google/cloud/__init__.py
google/cloud/spark/__init__.py
google/cloud/spark/bigquery/__init__.py
google/cloud/spark/bigquery/big_numeric_support.py
pydatafabric/__init__.py
pydatafabric/gcp.py
pydatafabric/github_utils.py
pydatafabric/lambda_autoload.py
pydatafabric/nes.py
pydatafabric/oracle.py
pydatafabric/spark_utils.py
pydatafabric/vault_utils.py
pydatafabric/webhook_utils.py
pydatafabric/ye.py
pydatafabric-0.4.41.dist-info/LICENSE
pydatafabric-0.4.41.dist-info/METADATA
pydatafabric-0.4.41.dist-info/WHEEL
pydatafabric-0.4.41.dist-info/entry_points.txt
pydatafabric-0.4.41.dist-info/top_level.txt
pydatafabric-0.4.41.dist-info/RECORD
