Metadata-Version: 2.1
Name: pydatafabric
Version: 0.4.41
Summary: SHINSEGAE DataFabric Python Package
Home-page: https://github.com/emartddt/dataplaltform-python-dist
Author: SHINSEGAE DataFabric
Author-email: admin@shinsegae.ai
License: MIT License
Platform: UNKNOWN
Classifier: Programming Language :: Python :: 3
Classifier: License :: OSI Approved :: MIT License
Classifier: Operating System :: OS Independent
Requires-Python: >=3.8,<3.11
Requires-Dist: thrift-sasl ==0.4.3
Requires-Dist: hvac ==0.11.2
Requires-Dist: pyhive[hive] ==0.6.5
Requires-Dist: pyarrow ==6.0.1
Requires-Dist: pandas ==1.3.5
Requires-Dist: db-dtypes <2.0.0,>=0.4.0
Requires-Dist: slackclient >=2.9.0
Requires-Dist: httplib2 >=0.20.0
Requires-Dist: click
Requires-Dist: PyGithub
Requires-Dist: pycryptodome
Requires-Dist: tabulate >=0.8.7
Requires-Dist: grpcio ==1.44.0
Requires-Dist: grpcio-status ==1.44.0
Requires-Dist: sqlalchemy ==1.4.48
Requires-Dist: packaging
Requires-Dist: tqdm >=4.63.0
Requires-Dist: ipywidgets
Requires-Dist: hmsclient-hive-3
Requires-Dist: dvc[s3] ==2.9.5
Requires-Dist: gcsfs
Requires-Dist: google-cloud-bigtable <3.0.0,>=2.0.0
Requires-Dist: google-cloud-monitoring <3.0.0,>=2.0.0
Requires-Dist: google-cloud-datacatalog <4.0.0,>=3.0.0
Requires-Dist: redis
Requires-Dist: testresources
Requires-Dist: python-dateutil >=2.8.2
Requires-Dist: requests <3.0.0,>=2.26.0
Requires-Dist: protobuf <4.0.0,>=3.0.0
Requires-Dist: google-cloud-bigquery <4.0.0,>=3.0.0
Requires-Dist: google-cloud-storage <3.0.0,>=2.0.0
Requires-Dist: google-auth <3.0.0,>=2.0.0
Requires-Dist: google-auth-oauthlib <0.5,>=0.4.1
Requires-Dist: google-api-core <3.0.0,>=2.0.0
Requires-Dist: google-api-python-client <3.0.0,>=2.34.0
Requires-Dist: google-cloud-core <3.0.0,>=2.0.0
Requires-Dist: google-cloud-common <2.0.0,>=1.0.0
Requires-Dist: googleapis-common-protos <2.0.0,>=1.55.0
Provides-Extra: emart
Requires-Dist: seaborn ==0.11.2 ; extra == 'emart'
Requires-Dist: matplotlib ==3.5.1 ; extra == 'emart'
Requires-Dist: openpyxl ==3.0.9 ; extra == 'emart'
Requires-Dist: xgboost ==1.5.2 ; extra == 'emart'
Requires-Dist: scikit-learn ==1.0.2 ; extra == 'emart'
Requires-Dist: bayesian-optimization ==1.2.0 ; extra == 'emart'
Requires-Dist: scipy <1.8.0,>=1.7.3 ; extra == 'emart'
Requires-Dist: numpy <1.22.2,>=1.15.0 ; extra == 'emart'
